liveserver/__init__.py
liveserver/ls.py
flask_liveserver-0.0.4.dist-info/LICENSE
flask_liveserver-0.0.4.dist-info/METADATA
flask_liveserver-0.0.4.dist-info/WHEEL
flask_liveserver-0.0.4.dist-info/top_level.txt
flask_liveserver-0.0.4.dist-info/RECORD
