Metadata-Version: 2.1
Name: flask_liveserver
Version: 0.0.4
Summary: Live Server in Flask.
Home-page: https://github.com/DevM63/flask_liveserver
Author: m63#7150
Author-email: jihonight@gmail.com
License: UNKNOWN
Platform: UNKNOWN
Classifier: License :: OSI Approved :: MIT License
